requests_api/__init__.py
requests_api/auth.py
requests_api/constants.py
requests_api/core.py
requests_api/errors.py
requests_api/version.py
requests_api-1.1.5.dist-info/LICENSE
requests_api-1.1.5.dist-info/METADATA
requests_api-1.1.5.dist-info/WHEEL
requests_api-1.1.5.dist-info/top_level.txt
requests_api-1.1.5.dist-info/RECORD
