Metadata-Version: 2.1
Name: requests-api
Version: 1.1.5
Summary: HTTP requests library.
Home-page: https://github.com/degagne/requests-api
Author: Deric Degagne
Author-email: deric.degagne@gmail.com
License: MIT
Platform: UNKNOWN
Classifier: Intended Audience :: Developers
Classifier: Intended Audience :: System Administrators
Classifier: Programming Language :: Python :: 3.6
Classifier: License :: OSI Approved :: MIT License
Requires-Python: >=3.6
License-File: LICENSE
Requires-Dist: urllib3
Requires-Dist: nested-lookup
Requires-Dist: requests (>=2.25)
Requires-Dist: requests-oauthlib (>=1.3)
Requires-Dist: requests-ntlm3
Requires-Dist: requests-kerberos (>=0.12)
